setup.py
pyjective/__init__.py
pyjective/congruence.py
pyjective/conic.py
pyjective/cross_ratio.py
pyjective/duality.py
pyjective/np_helpers.py
pyjective/transformation.py
pyjective.egg-info/PKG-INFO
pyjective.egg-info/SOURCES.txt
pyjective.egg-info/dependency_links.txt
pyjective.egg-info/not-zip-safe
pyjective.egg-info/top_level.txt