Metadata-Version: 1.0
Name: pyjective
Version: 0.1
Summary: A projective geometry library in Python
Home-page: https://github.com/PatrickFant/PyJective
Author: Patrick Fant
Author-email: pbfant@bu.edu
License: MIT
Platform: UNKNOWN
